rome/ROME.py
rome/__init__.py
romepy-0.1.4.dist-info/LICENSE
romepy-0.1.4.dist-info/METADATA
romepy-0.1.4.dist-info/WHEEL
romepy-0.1.4.dist-info/RECORD
