Metadata-Version: 2.1
Name: romepy
Version: 0.1.4
Summary: Python implementation of the Robust Multi-Modal Density Estimator (ROME)
Home-page: https://github.com/anna-meszaros/ROME
License: MIT
Author: Anna Meszaros
Author-email: ana.mesaros@gmail.com
Maintainer: anna-meszaros
Maintainer-email: ana.mesaros@gmail.com
Requires-Python: >=3.8,<4.0
Classifier: License :: OSI Approved :: MIT License
Classifier: Programming Language :: Python :: 3
Classifier: Programming Language :: Python :: 3.8
Classifier: Programming Language :: Python :: 3.9
Classifier: Programming Language :: Python :: 3.10
Classifier: Programming Language :: Python :: 3.11
Classifier: Programming Language :: Python :: 3.12
Requires-Dist: numpy (>=1.20.0,<2.0.0)
Requires-Dist: scikit-learn (>=1.2.2,<2.0.0)
Requires-Dist: scipy (>=1.0.0,<2.0.0)
Project-URL: Repository, https://github.com/anna-meszaros/ROME
